flash_rl/__init__.py
flash_rl/commands.py
flash_rl/flash_quantization.py
flash_rl/fp8loader.py
flash_rl/vllm_patch.py
flash_rl/configs/__init__.py
flash_rl/configs/bf16.py
flash_rl/configs/fp8.py
flash_rl/configs/int8.py
flash_llm_rl-1.0.3.dist-info/LICENSE
flash_llm_rl-1.0.3.dist-info/METADATA
flash_llm_rl-1.0.3.dist-info/WHEEL
flash_llm_rl-1.0.3.dist-info/entry_points.txt
flash_llm_rl-1.0.3.dist-info/top_level.txt
flash_llm_rl-1.0.3.dist-info/RECORD
