Metadata-Version: 2.1
Name: flash_llm_rl
Version: 1.0.3
Summary: flash llm rl
Home-page: https://github.com/yaof20/Flash-RL
Author: Lucas Liu
Author-email: llychinalz@gmail.com
License: License :: OSI Approved :: MIT License
Classifier: Development Status :: 2 - Pre-Alpha
Classifier: Intended Audience :: Developers
Classifier: Natural Language :: English
License-File: LICENSE
Requires-Dist: torch
Requires-Dist: transformers
Requires-Dist: vllm
Requires-Dist: huggingface-hub
